migcon/__init__.py
migcon/adjustment_utility.py
migcon/attachment.py
migcon/con2jb.py
migcon/content_manager.py
migcon/content_tree.py
migcon/div_fixups.py
migcon/drawio_handler.py
migcon/file_dups.py
migcon/file_processor.py
migcon/heading_info.py
migcon/link_and_table_handler.py
migcon/toc_generator.py
migcon-1.2.2.dist-info/LICENSE
migcon-1.2.2.dist-info/METADATA
migcon-1.2.2.dist-info/WHEEL
migcon-1.2.2.dist-info/entry_points.txt
migcon-1.2.2.dist-info/top_level.txt
migcon-1.2.2.dist-info/RECORD
