Metadata-Version: 2.1
Name: migcon
Version: 1.2.2
Summary: Utilities to migrate Confluence export to Sphinx, Juypter Book, etc.
Home-page: https://github.com/rappdw/migcon
Author: Daniel Rapp
Author-email: rappdw@gmail.com
License: Apache2
Platform: Windows
Platform: Linux
Platform: Mac OS-X
Classifier: Development Status :: 5 - Production/Stable
Classifier: Intended Audience :: Developers
Classifier: Topic :: Software Development :: Version Control :: Git
Classifier: Topic :: Software Development :: Libraries :: Python Modules
Classifier: License :: OSI Approved :: Apache Software License
Classifier: Programming Language :: Python :: 3.7
Classifier: Programming Language :: Python :: 3.8
Classifier: Programming Language :: Python :: 3.9
Classifier: Programming Language :: Python :: 3.10
License-File: LICENSE
Requires-Dist: anytree (>=2.8.0)
Requires-Dist: pyyaml (>=6.0)
Requires-Dist: markdownify (>=0.10.3)
Provides-Extra: dev
Requires-Dist: wheel (>=0.29) ; extra == 'dev'
